file_inspector/__init__.py
file_inspector/cli.py
file_inspector/file_info_extractor.py
file_inspector/file_reader.py
file_inspector/inspector.py
file_inspector/schema_validator.py
file_inspector/types.py
file_inspector/utils.py
file_inspector/formatter/__init__.py
file_inspector/formatter/html_formatter.py
file_inspector/formatter/json_formatter.py
file_inspector/formatter/markdown_formatter.py
file_inspector/formatter/slack_formatter.py
file_inspector-0.1.6.dist-info/METADATA
file_inspector-0.1.6.dist-info/WHEEL
file_inspector-0.1.6.dist-info/entry_points.txt
file_inspector-0.1.6.dist-info/top_level.txt
file_inspector-0.1.6.dist-info/RECORD
